pynescript/__about__.py
pynescript/__init__.py
pynescript/__main__.py
pynescript/py.typed
pynescript/ast/__init__.py
pynescript/ast/__main__.py
pynescript/ast/builder.py
pynescript/ast/collector.py
pynescript/ast/error.py
pynescript/ast/evaluator.py
pynescript/ast/helper.py
pynescript/ast/node.py
pynescript/ast/transformer.py
pynescript/ast/unparser.py
pynescript/ast/visitor.py
pynescript/ast/grammar/__init__.py
pynescript/ast/grammar/antlr4/__init__.py
pynescript/ast/grammar/antlr4/error_listener.py
pynescript/ast/grammar/antlr4/lexer.py
pynescript/ast/grammar/antlr4/listener.py
pynescript/ast/grammar/antlr4/parser.py
pynescript/ast/grammar/antlr4/visitor.py
pynescript/ast/grammar/antlr4/generated/PinescriptLexer.interp
pynescript/ast/grammar/antlr4/generated/PinescriptLexer.py
pynescript/ast/grammar/antlr4/generated/PinescriptLexer.tokens
pynescript/ast/grammar/antlr4/generated/PinescriptLexerBase.py
pynescript/ast/grammar/antlr4/generated/PinescriptParser.interp
pynescript/ast/grammar/antlr4/generated/PinescriptParser.py
pynescript/ast/grammar/antlr4/generated/PinescriptParser.tokens
pynescript/ast/grammar/antlr4/generated/PinescriptParserBase.py
pynescript/ast/grammar/antlr4/generated/PinescriptParserListener.py
pynescript/ast/grammar/antlr4/generated/PinescriptParserVisitor.py
pynescript/ast/grammar/antlr4/generated/__init__.py
pynescript/ast/grammar/antlr4/resource/PinescriptLexer.g4
pynescript/ast/grammar/antlr4/resource/PinescriptLexerBase.py
pynescript/ast/grammar/antlr4/resource/PinescriptParser.g4
pynescript/ast/grammar/antlr4/resource/PinescriptParserBase.py
pynescript/ast/grammar/antlr4/tool/__init__.py
pynescript/ast/grammar/antlr4/tool/generate.py
pynescript/ast/grammar/asdl/__init__.py
pynescript/ast/grammar/asdl/generated/PinescriptASTNode.py
pynescript/ast/grammar/asdl/generated/__init__.py
pynescript/ast/grammar/asdl/resource/Pinescript.asdl
pynescript/ast/grammar/asdl/tool/__init__.py
pynescript/ast/grammar/asdl/tool/asdlgen.py
pynescript-0.3.0.dist-info/METADATA
pynescript-0.3.0.dist-info/WHEEL
pynescript-0.3.0.dist-info/entry_points.txt
pynescript-0.3.0.dist-info/licenses/LICENSE
pynescript-0.3.0.dist-info/RECORD
