Metadata-Version: 2.4
Name: pynescript
Version: 0.3.0
Summary: Handle Pinescript using Python
Project-URL: Documentation, https://github.com/elbakramer/pynescript#readme
Project-URL: Issues, https://github.com/elbakramer/pynescript/issues
Project-URL: Source, https://github.com/elbakramer/pynescript
Author-email: Yunseong Hwang <kika1492@gmail.com>
Maintainer-email: Yunseong Hwang <kika1492@gmail.com>
License-Expression: LGPL-3.0-or-later
License-File: LICENSE
Keywords: pinescript,python,tradingview
Classifier: Development Status :: 2 - Pre-Alpha
Classifier: License :: OSI Approved :: GNU Lesser General Public License v3 or later (LGPLv3+)
Classifier: Programming Language :: Python
Classifier: Programming Language :: Python :: 3.10
Classifier: Programming Language :: Python :: 3.11
Classifier: Programming Language :: Python :: 3.12
Requires-Python: >=3.10
Requires-Dist: antlr4-python3-runtime>=4.13.2
Requires-Dist: click>=8.3.1
